{"exporting-type-declarations_monorepo.md":"EkCStRrp","reference_react-native_create-webview.md":"9E8tv_kC","backward-compatibility_new-method.md":"tHU6AyDk","what-is-webview-bridge.md":"0HU1hdIA","getting-started.md":"1Jfw8ogj","shared-state_react-native.md":"8DnR-3qh","example_react-navigation.md":"-wjM0Qv_","using-a-loose-native-method.md":"jt8UebSU","reference_web_link-bridge.md":"UbRskfOx","exporting-type-declarations_custom-declaration-file.md":"0of21og4","index.md":"BKAYgTyo","using-a-native-method.md":"KOOlrDDn","backward-compatibility_deprecated-method.md":"JdcsClfN","shared-state_vue.md":"MK9pbrAo","ssr_next-js-app-router.md":"CtLcAtA8","shared-state_vanilla.md":"YadGqNQV","using-a-web-method.md":"brDI7kkF","reference_web_register-web-method.md":"o_vRXT7C","shared-state_react.md":"vEQ6U1Nb","ssr_remix.md":"e52a0w0e"}
