{"shared-state_vue.md":"si9djV2t","using-a-web-method.md":"yFqgfMGK","ssr_remix.md":"0lCklcFI","example_react-navigation.md":"2PLa2RdF","reference_web_register-web-method.md":"Jj2fgHxo","using-a-loose-native-method.md":"MceMYIh_","exporting-type-declarations_custom-declaration-file.md":"4S8Fv285","getting-started.md":"4GIFe8zk","reference_react-native_create-webview.md":"ncuednNn","exporting-type-declarations_generate-declaration-file.md":"aj2Ez-0e","shared-state_vanilla.md":"5nC_jf9B","using-a-post-message.md":"c_r5GfGt","backward-compatibility_new-method.md":"ciq7wRKr","ssr_next-js-app-router.md":"B6HFJSl_","exporting-type-declarations_monorepo.md":"v3JcLnmT","what-is-webview-bridge.md":"KK0Ca6JH","reference_web_link-bridge.md":"hMaVBAnk","using-a-native-method.md":"DN-w1jNM","backward-compatibility_deprecated-method.md":"53HIVxBd","index.md":"0XxVrJ9a","shared-state_react.md":"J6kl2neW","shared-state_react-native.md":"7enjptWq"}
